schema_crawler/__init__.py
schema_crawler/schema_crawler_oracle.py
schema_crawler/schema_crawler_oracle_test.py
sqlmorph_api/__init__.py
sqlmorph_api/__main__.py
sqlmorph_api/sqlmorph_api.py
sqlmorph_api/sqlmorph_api_test.py
sqlmorph_api-2.4.1.dist-info/LICENSE
sqlmorph_api-2.4.1.dist-info/METADATA
sqlmorph_api-2.4.1.dist-info/WHEEL
sqlmorph_api-2.4.1.dist-info/top_level.txt
sqlmorph_api-2.4.1.dist-info/RECORD
