Metadata-Version: 2.1
Name: sqlmorph-api
Version: 2.4.1
Summary: SQLMorph translates from legacy SQL dialects to modern SQL dialects. This tool runs the translation in batch.
Home-page: https://www.phdata.io/sqlmorph/
Author: phData Internal Engineering
Author-email: sqlmorph-support@phdata.io
License: UNKNOWN
Platform: UNKNOWN
Classifier: Programming Language :: Python :: 3
Classifier: License :: OSI Approved :: Apache Software License
Classifier: Programming Language :: SQL
Classifier: Topic :: Database
Classifier: Operating System :: OS Independent
Requires-Python: >=3.2
